Achyut_calculator/__init__.py
Achyut_calculator-0.1.dist-info/LICENSE.txt
Achyut_calculator-0.1.dist-info/METADATA
Achyut_calculator-0.1.dist-info/WHEEL
Achyut_calculator-0.1.dist-info/top_level.txt
Achyut_calculator-0.1.dist-info/RECORD
