Metadata-Version: 2.1
Name: Achyut-calculator
Version: 0.1
Summary: This is a basic calculator
Author: Achyut Hegde
Author-email: aghmalakoppa@gmail.com
Classifier: Programming Language :: Python :: 3
Classifier: License :: OSI Approved :: MIT License
Classifier: Operating System :: OS Independent
License-File: LICENSE.txt
